{
  "entityType" : "NOTIFICATION_RULE",
  "entity" : {
    "additionalConfig" : {
      "description" : "Send notification to user when any alarm was assigned to him"
    },
    "enabled" : true,
    "externalId" : {
      "entityType" : "NOTIFICATION_RULE",
      "id" : "6a3bb400-da93-11ef-8e00-e370a74757c3"
    },
    "id" : {
      "entityType" : "NOTIFICATION_RULE",
      "id" : "6a3bb400-da93-11ef-8e00-e370a74757c3"
    },
    "name" : "Alarm assignment",
    "recipientsConfig" : {
      "targets" : [ "6a0d02e0-da93-11ef-8e00-e370a74757c3" ],
      "triggerType" : "ALARM_ASSIGNMENT"
    },
    "templateId" : {
      "entityType" : "NOTIFICATION_TEMPLATE",
      "id" : "6a3b65e0-da93-11ef-8e00-e370a74757c3"
    },
    "triggerConfig" : {
      "triggerType" : "ALARM_ASSIGNMENT",
      "alarmSeverities" : null,
      "alarmStatuses" : null,
      "alarmTypes" : null,
      "notifyOn" : [ "ASSIGNED" ],
      "triggerType" : "ALARM_ASSIGNMENT"
    },
    "triggerType" : "ALARM_ASSIGNMENT"
  }
}